betteria/__init__.py
betteria/cli.py
betteria-0.1.1.dist-info/METADATA
betteria-0.1.1.dist-info/WHEEL
betteria-0.1.1.dist-info/entry_points.txt
betteria-0.1.1.dist-info/RECORD
