Metadata-Version: 2.4
Name: betteria
Version: 0.1.1
Summary: A commandline tool to enhance PDFs from Internet Archive.
Requires-Python: >=3.9.0
Requires-Dist: img2pdf>=0.6.0
Requires-Dist: opencv-python>=4.11.0.86
Requires-Dist: pdf2image>=1.17.0
Requires-Dist: pillow>=11.2.1
Requires-Dist: tqdm>=4.67.1
Provides-Extra: dev
Requires-Dist: maturin; extra == 'dev'
Requires-Dist: pytest; extra == 'dev'
Requires-Dist: ruff; extra == 'dev'
Requires-Dist: twine; extra == 'dev'
